<mesh>
	<submeshes>
		<submesh material="ASPHALT_0" usesharedvertices="false">
			<faces count="4">
				<face v1="0" v2="1" v3="2"/>
				<face v1="1" v2="3" v3="2"/>
				<face v1="4" v2="5" v3="6"/>
				<face v1="5" v2="7" v3="6"/>
			</faces>
			<geometry vertexcount="8">
				<vertexbuffer positions="true" normals="true">
					<vertex>
						<position x="-1853.036255" y="0.000000" z="-4034.519043"/>
						<normal x="0.000000" y="1.000000" z="-0.000000"/>
					</vertex>
					<vertex>
						<position x="-1853.862305" y="0.000000" z="-4032.697510"/>
						<normal x="0.000000" y="1.000000" z="-0.000000"/>
					</vertex>
					<vertex>
						<position x="-1783.966431" y="0.000000" z="-3988.080811"/>
						<normal x="0.000000" y="1.000000" z="-0.000000"/>
					</vertex>
					<vertex>
						<position x="-1785.074341" y="0.000000" z="-3986.415527"/>
						<normal x="0.000000" y="1.000000" z="0.000000"/>
					</vertex>
					<vertex>
						<position x="-1853.903687" y="0.000000" z="-4032.606445"/>
						<normal x="0.000000" y="1.000000" z="-0.000000"/>
					</vertex>
					<vertex>
						<position x="-1854.729736" y="0.000000" z="-4030.785156"/>
						<normal x="0.000000" y="1.000000" z="-0.000000"/>
					</vertex>
					<vertex>
						<position x="-1785.129639" y="0.000000" z="-3986.332275"/>
						<normal x="0.000000" y="1.000000" z="-0.000000"/>
					</vertex>
					<vertex>
						<position x="-1786.237549" y="0.000000" z="-3984.667236"/>
						<normal x="0.000000" y="1.000000" z="0.000000"/>
					</vertex>
				</vertexbuffer>
			</geometry>
		</submesh>
	</submeshes>
</mesh>
