<mesh>
	<submeshes>
		<submesh material="ROAD_MARKING_DASHED_0" usesharedvertices="false">
			<faces count="2">
				<face v1="0" v2="1" v3="2"/>
				<face v1="1" v2="3" v3="2"/>
			</faces>
			<geometry vertexcount="4">
				<vertexbuffer positions="true" normals="true">
					<vertex>
						<position x="-375.784454" y="0.000000" z="-3795.094727"/>
						<normal x="-0.000000" y="1.000000" z="0.000000"/>
					</vertex>
					<vertex>
						<position x="-375.743561" y="0.000000" z="-3795.003418"/>
						<normal x="-0.000000" y="1.000000" z="0.000000"/>
					</vertex>
					<vertex>
						<position x="-351.998352" y="0.000000" z="-3798.853760"/>
						<normal x="-0.000000" y="1.000000" z="0.000000"/>
					</vertex>
					<vertex>
						<position x="-352.009644" y="0.000000" z="-3798.754395"/>
						<normal x="0.000000" y="1.000000" z="0.000000"/>
					</vertex>
				</vertexbuffer>
			</geometry>
		</submesh>
	</submeshes>
</mesh>
