<mesh>
	<submeshes>
		<submesh material="ASPHALT_0" usesharedvertices="false">
			<faces count="155">
				<face v1="0" v2="1" v3="2"/>
				<face v1="1" v2="3" v3="2"/>
				<face v1="4" v2="5" v3="6"/>
				<face v1="5" v2="7" v3="6"/>
				<face v1="2" v2="3" v3="8"/>
				<face v1="3" v2="9" v3="8"/>
				<face v1="6" v2="7" v3="10"/>
				<face v1="7" v2="11" v3="10"/>
				<face v1="8" v2="9" v3="12"/>
				<face v1="9" v2="13" v3="12"/>
				<face v1="14" v2="15" v3="16"/>
				<face v1="15" v2="17" v3="16"/>
				<face v1="18" v2="19" v3="20"/>
				<face v1="19" v2="21" v3="20"/>
				<face v1="10" v2="11" v3="22"/>
				<face v1="11" v2="23" v3="22"/>
				<face v1="24" v2="25" v3="26"/>
				<face v1="25" v2="27" v3="26"/>
				<face v1="28" v2="29" v3="30"/>
				<face v1="29" v2="31" v3="30"/>
				<face v1="20" v2="21" v3="32"/>
				<face v1="21" v2="33" v3="32"/>
				<face v1="30" v2="31" v3="34"/>
				<face v1="31" v2="35" v3="34"/>
				<face v1="32" v2="33" v3="36"/>
				<face v1="33" v2="37" v3="36"/>
				<face v1="34" v2="35" v3="38"/>
				<face v1="35" v2="39" v3="38"/>
				<face v1="36" v2="37" v3="40"/>
				<face v1="37" v2="41" v3="40"/>
				<face v1="42" v2="43" v3="44"/>
				<face v1="45" v2="41" v3="46"/>
				<face v1="41" v2="47" v3="46"/>
				<face v1="38" v2="39" v3="48"/>
				<face v1="39" v2="49" v3="48"/>
				<face v1="50" v2="51" v3="52"/>
				<face v1="51" v2="53" v3="52"/>
				<face v1="54" v2="55" v3="56"/>
				<face v1="55" v2="57" v3="56"/>
				<face v1="46" v2="47" v3="58"/>
				<face v1="47" v2="59" v3="58"/>
				<face v1="56" v2="57" v3="60"/>
				<face v1="57" v2="61" v3="60"/>
				<face v1="58" v2="59" v3="62"/>
				<face v1="59" v2="63" v3="62"/>
				<face v1="62" v2="63" v3="64"/>
				<face v1="63" v2="65" v3="64"/>
				<face v1="60" v2="61" v3="66"/>
				<face v1="61" v2="67" v3="66"/>
				<face v1="66" v2="67" v3="68"/>
				<face v1="67" v2="69" v3="68"/>
				<face v1="64" v2="65" v3="70"/>
				<face v1="65" v2="71" v3="70"/>
				<face v1="68" v2="69" v3="72"/>
				<face v1="69" v2="73" v3="72"/>
				<face v1="70" v2="71" v3="74"/>
				<face v1="71" v2="75" v3="74"/>
				<face v1="74" v2="75" v3="76"/>
				<face v1="75" v2="77" v3="76"/>
				<face v1="72" v2="73" v3="78"/>
				<face v1="73" v2="79" v3="78"/>
				<face v1="78" v2="79" v3="80"/>
				<face v1="79" v2="81" v3="80"/>
				<face v1="76" v2="77" v3="82"/>
				<face v1="77" v2="83" v3="82"/>
				<face v1="80" v2="81" v3="84"/>
				<face v1="81" v2="85" v3="84"/>
				<face v1="82" v2="83" v3="86"/>
				<face v1="83" v2="87" v3="86"/>
				<face v1="84" v2="85" v3="88"/>
				<face v1="85" v2="89" v3="88"/>
				<face v1="86" v2="87" v3="90"/>
				<face v1="87" v2="91" v3="90"/>
				<face v1="90" v2="91" v3="92"/>
				<face v1="91" v2="93" v3="92"/>
				<face v1="88" v2="89" v3="94"/>
				<face v1="89" v2="95" v3="94"/>
				<face v1="94" v2="95" v3="96"/>
				<face v1="95" v2="97" v3="96"/>
				<face v1="92" v2="93" v3="98"/>
				<face v1="93" v2="99" v3="98"/>
				<face v1="96" v2="97" v3="100"/>
				<face v1="97" v2="101" v3="100"/>
				<face v1="98" v2="99" v3="102"/>
				<face v1="99" v2="103" v3="102"/>
				<face v1="100" v2="101" v3="104"/>
				<face v1="101" v2="105" v3="104"/>
				<face v1="102" v2="103" v3="106"/>
				<face v1="103" v2="107" v3="106"/>
				<face v1="104" v2="105" v3="108"/>
				<face v1="105" v2="109" v3="108"/>
				<face v1="106" v2="107" v3="110"/>
				<face v1="107" v2="111" v3="110"/>
				<face v1="108" v2="109" v3="112"/>
				<face v1="109" v2="113" v3="112"/>
				<face v1="110" v2="111" v3="114"/>
				<face v1="111" v2="115" v3="114"/>
				<face v1="114" v2="115" v3="116"/>
				<face v1="115" v2="117" v3="116"/>
				<face v1="112" v2="113" v3="118"/>
				<face v1="113" v2="119" v3="118"/>
				<face v1="118" v2="119" v3="120"/>
				<face v1="119" v2="121" v3="120"/>
				<face v1="116" v2="117" v3="122"/>
				<face v1="117" v2="123" v3="122"/>
				<face v1="120" v2="121" v3="124"/>
				<face v1="121" v2="125" v3="124"/>
				<face v1="122" v2="123" v3="126"/>
				<face v1="123" v2="127" v3="126"/>
				<face v1="126" v2="127" v3="128"/>
				<face v1="127" v2="129" v3="128"/>
				<face v1="124" v2="125" v3="130"/>
				<face v1="125" v2="131" v3="130"/>
				<face v1="130" v2="131" v3="132"/>
				<face v1="131" v2="133" v3="132"/>
				<face v1="128" v2="129" v3="134"/>
				<face v1="129" v2="135" v3="134"/>
				<face v1="132" v2="133" v3="136"/>
				<face v1="133" v2="137" v3="136"/>
				<face v1="134" v2="135" v3="138"/>
				<face v1="135" v2="139" v3="138"/>
				<face v1="136" v2="137" v3="140"/>
				<face v1="137" v2="141" v3="140"/>
				<face v1="138" v2="139" v3="142"/>
				<face v1="139" v2="143" v3="142"/>
				<face v1="140" v2="141" v3="144"/>
				<face v1="141" v2="145" v3="144"/>
				<face v1="142" v2="143" v3="146"/>
				<face v1="143" v2="147" v3="146"/>
				<face v1="144" v2="145" v3="148"/>
				<face v1="145" v2="149" v3="148"/>
				<face v1="146" v2="147" v3="150"/>
				<face v1="147" v2="151" v3="150"/>
				<face v1="150" v2="151" v3="152"/>
				<face v1="151" v2="153" v3="152"/>
				<face v1="148" v2="149" v3="154"/>
				<face v1="149" v2="155" v3="154"/>
				<face v1="154" v2="155" v3="156"/>
				<face v1="155" v2="157" v3="156"/>
				<face v1="152" v2="153" v3="158"/>
				<face v1="153" v2="159" v3="158"/>
				<face v1="158" v2="159" v3="160"/>
				<face v1="159" v2="161" v3="160"/>
				<face v1="156" v2="157" v3="162"/>
				<face v1="157" v2="163" v3="162"/>
				<face v1="162" v2="163" v3="164"/>
				<face v1="163" v2="165" v3="164"/>
				<face v1="160" v2="161" v3="166"/>
				<face v1="161" v2="167" v3="166"/>
				<face v1="164" v2="165" v3="168"/>
				<face v1="165" v2="169" v3="168"/>
				<face v1="166" v2="167" v3="170"/>
				<face v1="167" v2="171" v3="170"/>
				<face v1="168" v2="169" v3="172"/>
				<face v1="169" v2="173" v3="172"/>
			</faces>
			<geometry vertexcount="174">
				<vertexbuffer positions="true" normals="true">
					<vertex>
						<position x="-58.687305" y="0.000000" z="379.451660"/>
						<normal x="-0.000000" y="1.000000" z="0.000000"/>
					</vertex>
					<vertex>
						<position x="-56.708149" y="0.000000" z="379.739655"/>
						<normal x="-0.000000" y="1.000000" z="0.000000"/>
					</vertex>
					<vertex>
						<position x="-55.950569" y="0.000000" z="360.726471"/>
						<normal x="-0.000000" y="1.000000" z="0.000000"/>
					</vertex>
					<vertex>
						<position x="-53.951965" y="0.000000" z="360.801147"/>
						<normal x="0.000000" y="1.000000" z="0.000000"/>
					</vertex>
					<vertex>
						<position x="-56.609192" y="0.000000" z="379.754059"/>
						<normal x="-0.000000" y="1.000000" z="0.000000"/>
					</vertex>
					<vertex>
						<position x="-54.630039" y="0.000000" z="380.042053"/>
						<normal x="-0.000000" y="1.000000" z="0.000000"/>
					</vertex>
					<vertex>
						<position x="-53.852036" y="0.000000" z="360.804871"/>
						<normal x="-0.000000" y="1.000000" z="0.000000"/>
					</vertex>
					<vertex>
						<position x="-51.853428" y="0.000000" z="360.879517"/>
						<normal x="0.000000" y="1.000000" z="0.000000"/>
					</vertex>
					<vertex>
						<position x="-68.445984" y="0.000000" z="182.200653"/>
						<normal x="-0.000000" y="1.000000" z="0.000000"/>
					</vertex>
					<vertex>
						<position x="-66.458679" y="0.000000" z="181.975632"/>
						<normal x="0.000000" y="1.000000" z="0.000000"/>
					</vertex>
					<vertex>
						<position x="-66.359314" y="0.000000" z="181.964371"/>
						<normal x="-0.000000" y="1.000000" z="0.000000"/>
					</vertex>
					<vertex>
						<position x="-64.372017" y="0.000000" z="181.739349"/>
						<normal x="0.000000" y="1.000000" z="0.000000"/>
					</vertex>
					<vertex>
						<position x="-78.160675" y="0.000000" z="120.317863"/>
						<normal x="0.000000" y="1.000000" z="0.000000"/>
					</vertex>
					<vertex>
						<position x="-76.184868" y="0.000000" z="120.007751"/>
						<normal x="0.000000" y="1.000000" z="0.000000"/>
					</vertex>
					<vertex>
						<position x="-78.160675" y="0.000000" z="120.317863"/>
						<normal x="0.000000" y="0.000000" z="0.000000"/>
					</vertex>
					<vertex>
						<position x="-76.184868" y="0.000000" z="120.007751"/>
						<normal x="0.000000" y="0.000000" z="0.000000"/>
					</vertex>
					<vertex>
						<position x="-78.160675" y="0.000000" z="120.317863"/>
						<normal x="0.000000" y="0.000000" z="0.000000"/>
					</vertex>
					<vertex>
						<position x="-76.184868" y="0.000000" z="120.007751"/>
						<normal x="0.000000" y="0.000000" z="0.000000"/>
					</vertex>
					<vertex>
						<position x="-78.160675" y="0.000000" z="120.317863"/>
						<normal x="0.000000" y="1.000000" z="0.000000"/>
					</vertex>
					<vertex>
						<position x="-76.184868" y="0.000000" z="120.007751"/>
						<normal x="0.000000" y="1.000000" z="0.000000"/>
					</vertex>
					<vertex>
						<position x="-98.469536" y="0.000000" z="-9.150560"/>
						<normal x="0.000000" y="1.000000" z="0.000000"/>
					</vertex>
					<vertex>
						<position x="-96.471939" y="0.000000" z="-9.248550"/>
						<normal x="0.000000" y="1.000000" z="0.000000"/>
					</vertex>
					<vertex>
						<position x="-76.086075" y="0.000000" z="119.992249"/>
						<normal x="0.000000" y="1.000000" z="0.000000"/>
					</vertex>
					<vertex>
						<position x="-74.110268" y="0.000000" z="119.682137"/>
						<normal x="0.000000" y="1.000000" z="0.000000"/>
					</vertex>
					<vertex>
						<position x="-76.086075" y="0.000000" z="119.992249"/>
						<normal x="0.000000" y="0.000000" z="0.000000"/>
					</vertex>
					<vertex>
						<position x="-74.110268" y="0.000000" z="119.682137"/>
						<normal x="0.000000" y="0.000000" z="0.000000"/>
					</vertex>
					<vertex>
						<position x="-76.086075" y="0.000000" z="119.992249"/>
						<normal x="0.000000" y="0.000000" z="0.000000"/>
					</vertex>
					<vertex>
						<position x="-74.110268" y="0.000000" z="119.682137"/>
						<normal x="0.000000" y="0.000000" z="0.000000"/>
					</vertex>
					<vertex>
						<position x="-76.086075" y="0.000000" z="119.992249"/>
						<normal x="0.000000" y="1.000000" z="0.000000"/>
					</vertex>
					<vertex>
						<position x="-74.110268" y="0.000000" z="119.682137"/>
						<normal x="0.000000" y="1.000000" z="0.000000"/>
					</vertex>
					<vertex>
						<position x="-96.372063" y="0.000000" z="-9.253449"/>
						<normal x="0.000000" y="1.000000" z="0.000000"/>
					</vertex>
					<vertex>
						<position x="-94.374458" y="0.000000" z="-9.351439"/>
						<normal x="0.000000" y="1.000000" z="0.000000"/>
					</vertex>
					<vertex>
						<position x="-94.713310" y="0.000000" z="-74.120354"/>
						<normal x="0.000000" y="1.000000" z="0.000000"/>
					</vertex>
					<vertex>
						<position x="-92.718864" y="0.000000" z="-74.269279"/>
						<normal x="0.000000" y="1.000000" z="0.000000"/>
					</vertex>
					<vertex>
						<position x="-92.619141" y="0.000000" z="-74.276726"/>
						<normal x="0.000000" y="1.000000" z="0.000000"/>
					</vertex>
					<vertex>
						<position x="-90.624687" y="0.000000" z="-74.425644"/>
						<normal x="0.000000" y="1.000000" z="0.000000"/>
					</vertex>
					<vertex>
						<position x="-110.867729" y="0.000000" z="-151.142792"/>
						<normal x="0.000000" y="1.000000" z="0.000000"/>
					</vertex>
					<vertex>
						<position x="-108.976288" y="0.000000" z="-151.792755"/>
						<normal x="0.000000" y="1.000000" z="0.000000"/>
					</vertex>
					<vertex>
						<position x="-108.881714" y="0.000000" z="-151.825256"/>
						<normal x="0.000000" y="1.000000" z="0.000000"/>
					</vertex>
					<vertex>
						<position x="-106.990273" y="0.000000" z="-152.475204"/>
						<normal x="0.000000" y="1.000000" z="0.000000"/>
					</vertex>
					<vertex>
						<position x="-124.571671" y="0.000000" z="-179.098602"/>
						<normal x="0.000000" y="1.000000" z="0.000000"/>
					</vertex>
					<vertex>
						<position x="-122.775383" y="0.000000" z="-179.978012"/>
						<normal x="0.000000" y="1.000000" z="0.000000"/>
					</vertex>
					<vertex>
						<position x="-124.571671" y="0.000000" z="-179.098602"/>
						<normal x="0.000000" y="0.000000" z="0.000000"/>
					</vertex>
					<vertex>
						<position x="-122.775383" y="0.000000" z="-179.978012"/>
						<normal x="0.000000" y="0.000000" z="0.000000"/>
					</vertex>
					<vertex>
						<position x="-124.571671" y="0.000000" z="-179.098602"/>
						<normal x="0.000000" y="0.000000" z="0.000000"/>
					</vertex>
					<vertex>
						<position x="-124.571671" y="0.000000" z="-179.098602"/>
						<normal x="0.000000" y="1.000000" z="0.000000"/>
					</vertex>
					<vertex>
						<position x="-138.251785" y="0.000000" z="-207.043457"/>
						<normal x="0.000000" y="1.000000" z="0.000000"/>
					</vertex>
					<vertex>
						<position x="-136.480286" y="0.000000" z="-207.971786"/>
						<normal x="0.000000" y="1.000000" z="0.000000"/>
					</vertex>
					<vertex>
						<position x="-122.685570" y="0.000000" z="-180.021988"/>
						<normal x="0.000000" y="1.000000" z="0.000000"/>
					</vertex>
					<vertex>
						<position x="-120.889282" y="0.000000" z="-180.901398"/>
						<normal x="0.000000" y="1.000000" z="0.000000"/>
					</vertex>
					<vertex>
						<position x="-122.685570" y="0.000000" z="-180.021988"/>
						<normal x="0.000000" y="0.000000" z="0.000000"/>
					</vertex>
					<vertex>
						<position x="-120.889282" y="0.000000" z="-180.901398"/>
						<normal x="0.000000" y="0.000000" z="0.000000"/>
					</vertex>
					<vertex>
						<position x="-122.685570" y="0.000000" z="-180.021988"/>
						<normal x="0.000000" y="0.000000" z="0.000000"/>
					</vertex>
					<vertex>
						<position x="-120.889282" y="0.000000" z="-180.901398"/>
						<normal x="0.000000" y="0.000000" z="0.000000"/>
					</vertex>
					<vertex>
						<position x="-122.685570" y="0.000000" z="-180.021988"/>
						<normal x="0.000000" y="1.000000" z="0.000000"/>
					</vertex>
					<vertex>
						<position x="-120.889282" y="0.000000" z="-180.901398"/>
						<normal x="0.000000" y="1.000000" z="0.000000"/>
					</vertex>
					<vertex>
						<position x="-136.391708" y="0.000000" z="-208.018204"/>
						<normal x="0.000000" y="1.000000" z="0.000000"/>
					</vertex>
					<vertex>
						<position x="-134.620209" y="0.000000" z="-208.946533"/>
						<normal x="0.000000" y="1.000000" z="0.000000"/>
					</vertex>
					<vertex>
						<position x="-197.000824" y="0.000000" z="-312.043488"/>
						<normal x="0.000000" y="1.000000" z="0.000000"/>
					</vertex>
					<vertex>
						<position x="-195.254654" y="0.000000" z="-313.018616"/>
						<normal x="0.000000" y="1.000000" z="0.000000"/>
					</vertex>
					<vertex>
						<position x="-195.167343" y="0.000000" z="-313.067383"/>
						<normal x="0.000000" y="1.000000" z="0.000000"/>
					</vertex>
					<vertex>
						<position x="-193.421188" y="0.000000" z="-314.042542"/>
						<normal x="0.000000" y="1.000000" z="0.000000"/>
					</vertex>
					<vertex>
						<position x="-211.790619" y="0.000000" z="-338.577118"/>
						<normal x="0.000000" y="1.000000" z="0.000000"/>
					</vertex>
					<vertex>
						<position x="-210.043671" y="0.000000" z="-339.550873"/>
						<normal x="0.000000" y="1.000000" z="0.000000"/>
					</vertex>
					<vertex>
						<position x="-239.639023" y="0.000000" z="-388.576355"/>
						<normal x="0.000000" y="1.000000" z="0.000000"/>
					</vertex>
					<vertex>
						<position x="-237.777542" y="0.000000" z="-389.307709"/>
						<normal x="0.000000" y="1.000000" z="0.000000"/>
					</vertex>
					<vertex>
						<position x="-209.956329" y="0.000000" z="-339.599548"/>
						<normal x="0.000000" y="1.000000" z="0.000000"/>
					</vertex>
					<vertex>
						<position x="-208.209381" y="0.000000" z="-340.573303"/>
						<normal x="0.000000" y="1.000000" z="0.000000"/>
					</vertex>
					<vertex>
						<position x="-237.684464" y="0.000000" z="-389.344269"/>
						<normal x="0.000000" y="1.000000" z="0.000000"/>
					</vertex>
					<vertex>
						<position x="-235.822983" y="0.000000" z="-390.075653"/>
						<normal x="0.000000" y="1.000000" z="0.000000"/>
					</vertex>
					<vertex>
						<position x="-254.719391" y="0.000000" z="-450.066071"/>
						<normal x="0.000000" y="1.000000" z="0.000000"/>
					</vertex>
					<vertex>
						<position x="-252.786331" y="0.000000" z="-450.579163"/>
						<normal x="0.000000" y="1.000000" z="0.000000"/>
					</vertex>
					<vertex>
						<position x="-252.689667" y="0.000000" z="-450.604828"/>
						<normal x="0.000000" y="1.000000" z="0.000000"/>
					</vertex>
					<vertex>
						<position x="-250.756607" y="0.000000" z="-451.117920"/>
						<normal x="0.000000" y="1.000000" z="0.000000"/>
					</vertex>
					<vertex>
						<position x="-263.123138" y="0.000000" z="-479.436096"/>
						<normal x="0.000000" y="1.000000" z="0.000000"/>
					</vertex>
					<vertex>
						<position x="-261.200317" y="0.000000" z="-479.986237"/>
						<normal x="0.000000" y="1.000000" z="0.000000"/>
					</vertex>
					<vertex>
						<position x="-303.468231" y="0.000000" z="-620.443909"/>
						<normal x="0.000000" y="1.000000" z="0.000000"/>
					</vertex>
					<vertex>
						<position x="-301.552887" y="0.000000" z="-621.019592"/>
						<normal x="0.000000" y="1.000000" z="0.000000"/>
					</vertex>
					<vertex>
						<position x="-261.104156" y="0.000000" z="-480.013763"/>
						<normal x="0.000000" y="1.000000" z="0.000000"/>
					</vertex>
					<vertex>
						<position x="-259.181335" y="0.000000" z="-480.563904"/>
						<normal x="0.000000" y="1.000000" z="0.000000"/>
					</vertex>
					<vertex>
						<position x="-301.457123" y="0.000000" z="-621.048401"/>
						<normal x="0.000000" y="1.000000" z="0.000000"/>
					</vertex>
					<vertex>
						<position x="-299.541748" y="0.000000" z="-621.624084"/>
						<normal x="0.000000" y="1.000000" z="0.000000"/>
					</vertex>
					<vertex>
						<position x="-332.313080" y="0.000000" z="-712.128845"/>
						<normal x="0.000000" y="1.000000" z="0.000000"/>
					</vertex>
					<vertex>
						<position x="-330.321777" y="0.000000" z="-712.315308"/>
						<normal x="0.000000" y="1.000000" z="0.000000"/>
					</vertex>
					<vertex>
						<position x="-330.222229" y="0.000000" z="-712.324646"/>
						<normal x="0.000000" y="1.000000" z="0.000000"/>
					</vertex>
					<vertex>
						<position x="-328.230927" y="0.000000" z="-712.511169"/>
						<normal x="0.000000" y="1.000000" z="0.000000"/>
					</vertex>
					<vertex>
						<position x="-326.062042" y="0.000000" z="-764.683899"/>
						<normal x="0.000000" y="1.000000" z="0.000000"/>
					</vertex>
					<vertex>
						<position x="-324.067841" y="0.000000" z="-764.836182"/>
						<normal x="0.000000" y="1.000000" z="0.000000"/>
					</vertex>
					<vertex>
						<position x="-323.968140" y="0.000000" z="-764.843811"/>
						<normal x="0.000000" y="1.000000" z="0.000000"/>
					</vertex>
					<vertex>
						<position x="-321.973938" y="0.000000" z="-764.996094"/>
						<normal x="0.000000" y="1.000000" z="0.000000"/>
					</vertex>
					<vertex>
						<position x="-330.204254" y="0.000000" z="-779.451355"/>
						<normal x="0.000000" y="1.000000" z="0.000000"/>
					</vertex>
					<vertex>
						<position x="-328.277222" y="0.000000" z="-779.986633"/>
						<normal x="0.000000" y="1.000000" z="0.000000"/>
					</vertex>
					<vertex>
						<position x="-338.376343" y="0.000000" z="-808.985657"/>
						<normal x="0.000000" y="1.000000" z="0.000000"/>
					</vertex>
					<vertex>
						<position x="-336.570160" y="0.000000" z="-809.844543"/>
						<normal x="0.000000" y="1.000000" z="0.000000"/>
					</vertex>
					<vertex>
						<position x="-328.180847" y="0.000000" z="-780.013367"/>
						<normal x="0.000000" y="1.000000" z="0.000000"/>
					</vertex>
					<vertex>
						<position x="-326.253815" y="0.000000" z="-780.548645"/>
						<normal x="0.000000" y="1.000000" z="0.000000"/>
					</vertex>
					<vertex>
						<position x="-336.479858" y="0.000000" z="-809.887451"/>
						<normal x="0.000000" y="1.000000" z="0.000000"/>
					</vertex>
					<vertex>
						<position x="-334.673645" y="0.000000" z="-810.746338"/>
						<normal x="0.000000" y="1.000000" z="0.000000"/>
					</vertex>
					<vertex>
						<position x="-359.592346" y="0.000000" z="-838.883789"/>
						<normal x="0.000000" y="1.000000" z="0.000000"/>
					</vertex>
					<vertex>
						<position x="-357.823242" y="0.000000" z="-839.816650"/>
						<normal x="0.000000" y="1.000000" z="0.000000"/>
					</vertex>
					<vertex>
						<position x="-357.734772" y="0.000000" z="-839.863342"/>
						<normal x="0.000000" y="1.000000" z="0.000000"/>
					</vertex>
					<vertex>
						<position x="-355.965668" y="0.000000" z="-840.796204"/>
						<normal x="0.000000" y="1.000000" z="0.000000"/>
					</vertex>
					<vertex>
						<position x="-389.732269" y="0.000000" z="-920.456360"/>
						<normal x="0.000000" y="1.000000" z="0.000000"/>
					</vertex>
					<vertex>
						<position x="-387.840302" y="0.000000" z="-921.104797"/>
						<normal x="0.000000" y="1.000000" z="0.000000"/>
					</vertex>
					<vertex>
						<position x="-387.745697" y="0.000000" z="-921.137207"/>
						<normal x="0.000000" y="1.000000" z="0.000000"/>
					</vertex>
					<vertex>
						<position x="-385.853729" y="0.000000" z="-921.785645"/>
						<normal x="0.000000" y="1.000000" z="0.000000"/>
					</vertex>
					<vertex>
						<position x="-413.529327" y="0.000000" z="-995.613403"/>
						<normal x="0.000000" y="1.000000" z="0.000000"/>
					</vertex>
					<vertex>
						<position x="-411.601196" y="0.000000" z="-996.144714"/>
						<normal x="0.000000" y="1.000000" z="0.000000"/>
					</vertex>
					<vertex>
						<position x="-411.504791" y="0.000000" z="-996.171265"/>
						<normal x="0.000000" y="1.000000" z="0.000000"/>
					</vertex>
					<vertex>
						<position x="-409.576660" y="0.000000" z="-996.702637"/>
						<normal x="0.000000" y="1.000000" z="0.000000"/>
					</vertex>
					<vertex>
						<position x="-428.498901" y="0.000000" z="-1059.261230"/>
						<normal x="0.000000" y="1.000000" z="0.000000"/>
					</vertex>
					<vertex>
						<position x="-426.607300" y="0.000000" z="-1059.910767"/>
						<normal x="0.000000" y="1.000000" z="0.000000"/>
					</vertex>
					<vertex>
						<position x="-426.512695" y="0.000000" z="-1059.943237"/>
						<normal x="0.000000" y="1.000000" z="0.000000"/>
					</vertex>
					<vertex>
						<position x="-424.621094" y="0.000000" z="-1060.592773"/>
						<normal x="0.000000" y="1.000000" z="0.000000"/>
					</vertex>
					<vertex>
						<position x="-437.637573" y="0.000000" z="-1079.144775"/>
						<normal x="0.000000" y="1.000000" z="0.000000"/>
					</vertex>
					<vertex>
						<position x="-435.819946" y="0.000000" z="-1079.979126"/>
						<normal x="0.000000" y="1.000000" z="0.000000"/>
					</vertex>
					<vertex>
						<position x="-463.449493" y="0.000000" z="-1135.374390"/>
						<normal x="0.000000" y="1.000000" z="0.000000"/>
					</vertex>
					<vertex>
						<position x="-461.619751" y="0.000000" z="-1136.181763"/>
						<normal x="0.000000" y="1.000000" z="0.000000"/>
					</vertex>
					<vertex>
						<position x="-435.729065" y="0.000000" z="-1080.020874"/>
						<normal x="0.000000" y="1.000000" z="0.000000"/>
					</vertex>
					<vertex>
						<position x="-433.911438" y="0.000000" z="-1080.855225"/>
						<normal x="0.000000" y="1.000000" z="0.000000"/>
					</vertex>
					<vertex>
						<position x="-461.528259" y="0.000000" z="-1136.222168"/>
						<normal x="0.000000" y="1.000000" z="0.000000"/>
					</vertex>
					<vertex>
						<position x="-459.698486" y="0.000000" z="-1137.029663"/>
						<normal x="0.000000" y="1.000000" z="0.000000"/>
					</vertex>
					<vertex>
						<position x="-494.486237" y="0.000000" z="-1208.763428"/>
						<normal x="0.000000" y="1.000000" z="0.000000"/>
					</vertex>
					<vertex>
						<position x="-492.880157" y="0.000000" z="-1209.955200"/>
						<normal x="0.000000" y="1.000000" z="0.000000"/>
					</vertex>
					<vertex>
						<position x="-492.799835" y="0.000000" z="-1210.014771"/>
						<normal x="0.000000" y="1.000000" z="0.000000"/>
					</vertex>
					<vertex>
						<position x="-491.193756" y="0.000000" z="-1211.206665"/>
						<normal x="0.000000" y="1.000000" z="0.000000"/>
					</vertex>
					<vertex>
						<position x="-511.312469" y="0.000000" z="-1222.712158"/>
						<normal x="0.000000" y="1.000000" z="0.000000"/>
					</vertex>
					<vertex>
						<position x="-510.032013" y="0.000000" z="-1224.248535"/>
						<normal x="0.000000" y="1.000000" z="0.000000"/>
					</vertex>
					<vertex>
						<position x="-523.759521" y="0.000000" z="-1233.158813"/>
						<normal x="0.000000" y="1.000000" z="0.000000"/>
					</vertex>
					<vertex>
						<position x="-522.870239" y="0.000000" z="-1234.950195"/>
						<normal x="0.000000" y="1.000000" z="0.000000"/>
					</vertex>
					<vertex>
						<position x="-509.967987" y="0.000000" z="-1224.325317"/>
						<normal x="0.000000" y="1.000000" z="0.000000"/>
					</vertex>
					<vertex>
						<position x="-508.687531" y="0.000000" z="-1225.861694"/>
						<normal x="0.000000" y="1.000000" z="0.000000"/>
					</vertex>
					<vertex>
						<position x="-522.825745" y="0.000000" z="-1235.039795"/>
						<normal x="0.000000" y="1.000000" z="0.000000"/>
					</vertex>
					<vertex>
						<position x="-521.936462" y="0.000000" z="-1236.831177"/>
						<normal x="0.000000" y="1.000000" z="0.000000"/>
					</vertex>
					<vertex>
						<position x="-620.944092" y="0.000000" z="-1255.526611"/>
						<normal x="0.000000" y="1.000000" z="0.000000"/>
					</vertex>
					<vertex>
						<position x="-620.402527" y="0.000000" z="-1257.451904"/>
						<normal x="0.000000" y="1.000000" z="0.000000"/>
					</vertex>
					<vertex>
						<position x="-620.375488" y="0.000000" z="-1257.548096"/>
						<normal x="0.000000" y="1.000000" z="0.000000"/>
					</vertex>
					<vertex>
						<position x="-619.833923" y="0.000000" z="-1259.473389"/>
						<normal x="0.000000" y="1.000000" z="0.000000"/>
					</vertex>
					<vertex>
						<position x="-647.581177" y="0.000000" z="-1264.422607"/>
						<normal x="0.000000" y="1.000000" z="0.000000"/>
					</vertex>
					<vertex>
						<position x="-646.678589" y="0.000000" z="-1266.207397"/>
						<normal x="0.000000" y="1.000000" z="0.000000"/>
					</vertex>
					<vertex>
						<position x="-646.633423" y="0.000000" z="-1266.296631"/>
						<normal x="0.000000" y="1.000000" z="0.000000"/>
					</vertex>
					<vertex>
						<position x="-645.730774" y="0.000000" z="-1268.081299"/>
						<normal x="0.000000" y="1.000000" z="0.000000"/>
					</vertex>
					<vertex>
						<position x="-690.766479" y="0.000000" z="-1294.988037"/>
						<normal x="0.000000" y="1.000000" z="0.000000"/>
					</vertex>
					<vertex>
						<position x="-689.208923" y="0.000000" z="-1296.242676"/>
						<normal x="0.000000" y="1.000000" z="0.000000"/>
					</vertex>
					<vertex>
						<position x="-689.131042" y="0.000000" z="-1296.305420"/>
						<normal x="0.000000" y="1.000000" z="0.000000"/>
					</vertex>
					<vertex>
						<position x="-687.573547" y="0.000000" z="-1297.560059"/>
						<normal x="0.000000" y="1.000000" z="0.000000"/>
					</vertex>
					<vertex>
						<position x="-707.723572" y="0.000000" z="-1334.864624"/>
						<normal x="0.000000" y="1.000000" z="0.000000"/>
					</vertex>
					<vertex>
						<position x="-705.889832" y="0.000000" z="-1335.663086"/>
						<normal x="0.000000" y="1.000000" z="0.000000"/>
					</vertex>
					<vertex>
						<position x="-705.798157" y="0.000000" z="-1335.703003"/>
						<normal x="0.000000" y="1.000000" z="0.000000"/>
					</vertex>
					<vertex>
						<position x="-703.964417" y="0.000000" z="-1336.501343"/>
						<normal x="0.000000" y="1.000000" z="0.000000"/>
					</vertex>
					<vertex>
						<position x="-727.559937" y="0.000000" z="-1379.162231"/>
						<normal x="0.000000" y="1.000000" z="0.000000"/>
					</vertex>
					<vertex>
						<position x="-725.734619" y="0.000000" z="-1379.979614"/>
						<normal x="0.000000" y="1.000000" z="0.000000"/>
					</vertex>
					<vertex>
						<position x="-745.137024" y="0.000000" z="-1418.441650"/>
						<normal x="0.000000" y="1.000000" z="0.000000"/>
					</vertex>
					<vertex>
						<position x="-743.406250" y="0.000000" z="-1419.443970"/>
						<normal x="0.000000" y="1.000000" z="0.000000"/>
					</vertex>
					<vertex>
						<position x="-725.643311" y="0.000000" z="-1380.020386"/>
						<normal x="0.000000" y="1.000000" z="0.000000"/>
					</vertex>
					<vertex>
						<position x="-723.817993" y="0.000000" z="-1380.837769"/>
						<normal x="0.000000" y="1.000000" z="0.000000"/>
					</vertex>
					<vertex>
						<position x="-743.319702" y="0.000000" z="-1419.494019"/>
						<normal x="0.000000" y="1.000000" z="0.000000"/>
					</vertex>
					<vertex>
						<position x="-741.588989" y="0.000000" z="-1420.496338"/>
						<normal x="0.000000" y="1.000000" z="0.000000"/>
					</vertex>
					<vertex>
						<position x="-811.657959" y="0.000000" z="-1509.894409"/>
						<normal x="0.000000" y="1.000000" z="0.000000"/>
					</vertex>
					<vertex>
						<position x="-810.040466" y="0.000000" z="-1511.070679"/>
						<normal x="0.000000" y="1.000000" z="0.000000"/>
					</vertex>
					<vertex>
						<position x="-815.050171" y="0.000000" z="-1514.558960"/>
						<normal x="0.000000" y="1.000000" z="0.000000"/>
					</vertex>
					<vertex>
						<position x="-813.431458" y="0.000000" z="-1515.733643"/>
						<normal x="0.000000" y="1.000000" z="0.000000"/>
					</vertex>
					<vertex>
						<position x="-809.959534" y="0.000000" z="-1511.129517"/>
						<normal x="0.000000" y="1.000000" z="0.000000"/>
					</vertex>
					<vertex>
						<position x="-808.342041" y="0.000000" z="-1512.305786"/>
						<normal x="0.000000" y="1.000000" z="0.000000"/>
					</vertex>
					<vertex>
						<position x="-813.350525" y="0.000000" z="-1515.792358"/>
						<normal x="0.000000" y="1.000000" z="0.000000"/>
					</vertex>
					<vertex>
						<position x="-811.731812" y="0.000000" z="-1516.967041"/>
						<normal x="0.000000" y="1.000000" z="0.000000"/>
					</vertex>
					<vertex>
						<position x="-867.913086" y="0.000000" z="-1587.848877"/>
						<normal x="0.000000" y="1.000000" z="0.000000"/>
					</vertex>
					<vertex>
						<position x="-865.960815" y="0.000000" z="-1588.283203"/>
						<normal x="0.000000" y="1.000000" z="0.000000"/>
					</vertex>
					<vertex>
						<position x="-865.863220" y="0.000000" z="-1588.304810"/>
						<normal x="0.000000" y="1.000000" z="0.000000"/>
					</vertex>
					<vertex>
						<position x="-863.910889" y="0.000000" z="-1588.739136"/>
						<normal x="0.000000" y="1.000000" z="0.000000"/>
					</vertex>
					<vertex>
						<position x="-857.244507" y="0.000000" z="-1644.518433"/>
						<normal x="0.000000" y="1.000000" z="0.000000"/>
					</vertex>
					<vertex>
						<position x="-855.280151" y="0.000000" z="-1644.142700"/>
						<normal x="0.000000" y="1.000000" z="0.000000"/>
					</vertex>
					<vertex>
						<position x="-855.181885" y="0.000000" z="-1644.123901"/>
						<normal x="0.000000" y="1.000000" z="0.000000"/>
					</vertex>
					<vertex>
						<position x="-853.217529" y="0.000000" z="-1643.748169"/>
						<normal x="0.000000" y="1.000000" z="0.000000"/>
					</vertex>
				</vertexbuffer>
			</geometry>
		</submesh>
	</submeshes>
</mesh>
