<mesh>
	<submeshes>
		<submesh material="TERRAIN_DEFAULT_0" usesharedvertices="false">
			<faces count="242">
				<face v1="0" v2="1" v3="2"/>
				<face v1="3" v2="0" v3="2"/>
				<face v1="4" v2="3" v3="2"/>
				<face v1="5" v2="3" v3="4"/>
				<face v1="5" v2="4" v3="6"/>
				<face v1="6" v2="4" v3="7"/>
				<face v1="8" v2="6" v3="7"/>
				<face v1="9" v2="8" v3="7"/>
				<face v1="10" v2="9" v3="7"/>
				<face v1="10" v2="7" v3="11"/>
				<face v1="9" v2="10" v3="12"/>
				<face v1="10" v2="11" v3="13"/>
				<face v1="10" v2="13" v3="12"/>
				<face v1="13" v2="11" v3="14"/>
				<face v1="12" v2="13" v3="15"/>
				<face v1="13" v2="14" v3="15"/>
				<face v1="12" v2="15" v3="16"/>
				<face v1="15" v2="14" v3="17"/>
				<face v1="15" v2="17" v3="16"/>
				<face v1="18" v2="12" v3="16"/>
				<face v1="16" v2="17" v3="19"/>
				<face v1="16" v2="20" v3="18"/>
				<face v1="16" v2="19" v3="20"/>
				<face v1="18" v2="20" v3="21"/>
				<face v1="20" v2="19" v3="22"/>
				<face v1="20" v2="22" v3="21"/>
				<face v1="18" v2="21" v3="23"/>
				<face v1="21" v2="22" v3="24"/>
				<face v1="23" v2="21" v3="25"/>
				<face v1="18" v2="23" v3="26"/>
				<face v1="21" v2="24" v3="25"/>
				<face v1="23" v2="25" v3="27"/>
				<face v1="23" v2="28" v3="26"/>
				<face v1="29" v2="18" v3="26"/>
				<face v1="25" v2="24" v3="30"/>
				<face v1="27" v2="25" v3="31"/>
				<face v1="23" v2="27" v3="28"/>
				<face v1="26" v2="28" v3="32"/>
				<face v1="29" v2="26" v3="33"/>
				<face v1="25" v2="30" v3="31"/>
				<face v1="27" v2="31" v3="34"/>
				<face v1="28" v2="27" v3="34"/>
				<face v1="28" v2="34" v3="32"/>
				<face v1="26" v2="32" v3="33"/>
				<face v1="29" v2="33" v3="35"/>
				<face v1="31" v2="30" v3="36"/>
				<face v1="34" v2="31" v3="37"/>
				<face v1="32" v2="34" v3="38"/>
				<face v1="33" v2="32" v3="39"/>
				<face v1="35" v2="33" v3="40"/>
				<face v1="29" v2="35" v3="41"/>
				<face v1="31" v2="36" v3="37"/>
				<face v1="34" v2="37" v3="38"/>
				<face v1="32" v2="38" v3="39"/>
				<face v1="33" v2="39" v3="40"/>
				<face v1="35" v2="40" v3="42"/>
				<face v1="41" v2="35" v3="42"/>
				<face v1="29" v2="41" v3="43"/>
				<face v1="41" v2="42" v3="44"/>
				<face v1="43" v2="41" v3="45"/>
				<face v1="41" v2="44" v3="45"/>
				<face v1="43" v2="45" v3="46"/>
				<face v1="47" v2="48" v3="49"/>
				<face v1="49" v2="48" v3="50"/>
				<face v1="47" v2="51" v3="48"/>
				<face v1="48" v2="52" v3="50"/>
				<face v1="49" v2="50" v3="53"/>
				<face v1="51" v2="54" v3="48"/>
				<face v1="50" v2="52" v3="55"/>
				<face v1="48" v2="54" v3="52"/>
				<face v1="53" v2="50" v3="56"/>
				<face v1="51" v2="57" v3="54"/>
				<face v1="52" v2="58" v3="55"/>
				<face v1="50" v2="55" v3="56"/>
				<face v1="54" v2="59" v3="52"/>
				<face v1="53" v2="56" v3="60"/>
				<face v1="57" v2="61" v3="54"/>
				<face v1="55" v2="58" v3="62"/>
				<face v1="52" v2="59" v3="58"/>
				<face v1="56" v2="55" v3="63"/>
				<face v1="54" v2="61" v3="59"/>
				<face v1="60" v2="56" v3="64"/>
				<face v1="57" v2="65" v3="61"/>
				<face v1="58" v2="66" v3="62"/>
				<face v1="55" v2="62" v3="63"/>
				<face v1="59" v2="67" v3="58"/>
				<face v1="56" v2="63" v3="64"/>
				<face v1="61" v2="68" v3="59"/>
				<face v1="60" v2="64" v3="69"/>
				<face v1="65" v2="70" v3="61"/>
				<face v1="62" v2="66" v3="71"/>
				<face v1="58" v2="67" v3="66"/>
				<face v1="63" v2="62" v3="72"/>
				<face v1="59" v2="68" v3="67"/>
				<face v1="64" v2="63" v3="73"/>
				<face v1="61" v2="70" v3="68"/>
				<face v1="69" v2="64" v3="74"/>
				<face v1="65" v2="75" v3="70"/>
				<face v1="66" v2="76" v3="71"/>
				<face v1="62" v2="71" v3="72"/>
				<face v1="67" v2="77" v3="66"/>
				<face v1="63" v2="72" v3="73"/>
				<face v1="68" v2="78" v3="67"/>
				<face v1="64" v2="73" v3="74"/>
				<face v1="70" v2="79" v3="68"/>
				<face v1="69" v2="74" v3="80"/>
				<face v1="70" v2="75" v3="81"/>
				<face v1="71" v2="76" v3="82"/>
				<face v1="66" v2="77" v3="76"/>
				<face v1="72" v2="71" v3="83"/>
				<face v1="67" v2="78" v3="77"/>
				<face v1="73" v2="72" v3="84"/>
				<face v1="68" v2="79" v3="78"/>
				<face v1="74" v2="73" v3="85"/>
				<face v1="70" v2="86" v3="79"/>
				<face v1="80" v2="74" v3="87"/>
				<face v1="70" v2="81" v3="88"/>
				<face v1="76" v2="89" v3="82"/>
				<face v1="71" v2="82" v3="83"/>
				<face v1="77" v2="90" v3="76"/>
				<face v1="72" v2="83" v3="84"/>
				<face v1="78" v2="91" v3="77"/>
				<face v1="73" v2="84" v3="85"/>
				<face v1="79" v2="92" v3="78"/>
				<face v1="74" v2="85" v3="87"/>
				<face v1="86" v2="93" v3="79"/>
				<face v1="88" v2="86" v3="70"/>
				<face v1="80" v2="87" v3="94"/>
				<face v1="82" v2="89" v3="95"/>
				<face v1="76" v2="90" v3="89"/>
				<face v1="83" v2="82" v3="96"/>
				<face v1="77" v2="91" v3="90"/>
				<face v1="84" v2="83" v3="97"/>
				<face v1="78" v2="92" v3="91"/>
				<face v1="85" v2="84" v3="98"/>
				<face v1="79" v2="93" v3="92"/>
				<face v1="87" v2="85" v3="99"/>
				<face v1="86" v2="100" v3="93"/>
				<face v1="88" v2="101" v3="86"/>
				<face v1="94" v2="87" v3="102"/>
				<face v1="89" v2="103" v3="95"/>
				<face v1="82" v2="95" v3="96"/>
				<face v1="90" v2="104" v3="89"/>
				<face v1="83" v2="96" v3="97"/>
				<face v1="91" v2="105" v3="90"/>
				<face v1="84" v2="97" v3="98"/>
				<face v1="92" v2="106" v3="91"/>
				<face v1="85" v2="98" v3="99"/>
				<face v1="93" v2="107" v3="92"/>
				<face v1="87" v2="99" v3="102"/>
				<face v1="100" v2="108" v3="93"/>
				<face v1="101" v2="100" v3="86"/>
				<face v1="94" v2="102" v3="109"/>
				<face v1="110" v2="95" v3="103"/>
				<face v1="89" v2="104" v3="103"/>
				<face v1="96" v2="95" v3="110"/>
				<face v1="90" v2="105" v3="104"/>
				<face v1="97" v2="96" v3="111"/>
				<face v1="91" v2="106" v3="105"/>
				<face v1="98" v2="97" v3="112"/>
				<face v1="92" v2="107" v3="106"/>
				<face v1="99" v2="98" v3="113"/>
				<face v1="93" v2="108" v3="107"/>
				<face v1="102" v2="99" v3="114"/>
				<face v1="100" v2="115" v3="108"/>
				<face v1="101" v2="116" v3="100"/>
				<face v1="109" v2="102" v3="117"/>
				<face v1="110" v2="103" v3="118"/>
				<face v1="103" v2="104" v3="119"/>
				<face v1="111" v2="96" v3="110"/>
				<face v1="105" v2="119" v3="104"/>
				<face v1="97" v2="111" v3="112"/>
				<face v1="106" v2="120" v3="105"/>
				<face v1="98" v2="112" v3="113"/>
				<face v1="107" v2="121" v3="106"/>
				<face v1="99" v2="113" v3="114"/>
				<face v1="108" v2="122" v3="107"/>
				<face v1="102" v2="114" v3="117"/>
				<face v1="123" v2="108" v3="115"/>
				<face v1="116" v2="115" v3="100"/>
				<face v1="109" v2="117" v3="124"/>
				<face v1="103" v2="119" v3="118"/>
				<face v1="110" v2="125" v3="111"/>
				<face v1="105" v2="120" v3="119"/>
				<face v1="125" v2="112" v3="111"/>
				<face v1="106" v2="121" v3="120"/>
				<face v1="125" v2="113" v3="112"/>
				<face v1="107" v2="122" v3="121"/>
				<face v1="114" v2="113" v3="125"/>
				<face v1="108" v2="126" v3="122"/>
				<face v1="117" v2="114" v3="127"/>
				<face v1="116" v2="123" v3="115"/>
				<face v1="108" v2="123" v3="126"/>
				<face v1="124" v2="117" v3="128"/>
				<face v1="119" v2="120" v3="118"/>
				<face v1="129" v2="125" v3="110"/>
				<face v1="120" v2="121" v3="130"/>
				<face v1="122" v2="130" v3="121"/>
				<face v1="127" v2="114" v3="125"/>
				<face v1="122" v2="126" v3="131"/>
				<face v1="117" v2="127" v3="128"/>
				<face v1="126" v2="123" v3="132"/>
				<face v1="124" v2="128" v3="133"/>
				<face v1="118" v2="120" v3="130"/>
				<face v1="129" v2="127" v3="125"/>
				<face v1="130" v2="122" v3="131"/>
				<face v1="134" v2="131" v3="126"/>
				<face v1="135" v2="128" v3="127"/>
				<face v1="132" v2="136" v3="126"/>
				<face v1="133" v2="128" v3="137"/>
				<face v1="135" v2="127" v3="129"/>
				<face v1="138" v2="134" v3="126"/>
				<face v1="128" v2="135" v3="137"/>
				<face v1="136" v2="139" v3="126"/>
				<face v1="133" v2="137" v3="140"/>
				<face v1="139" v2="138" v3="126"/>
				<face v1="135" v2="141" v3="137"/>
				<face v1="142" v2="143" v3="144"/>
				<face v1="144" v2="143" v3="145"/>
				<face v1="142" v2="144" v3="146"/>
				<face v1="147" v2="144" v3="145"/>
				<face v1="146" v2="144" v3="147"/>
				<face v1="148" v2="142" v3="146"/>
				<face v1="146" v2="147" v3="149"/>
				<face v1="150" v2="148" v3="146"/>
				<face v1="149" v2="147" v3="151"/>
				<face v1="150" v2="152" v3="148"/>
				<face v1="149" v2="151" v3="153"/>
				<face v1="152" v2="154" v3="148"/>
				<face v1="155" v2="156" v3="157"/>
				<face v1="156" v2="158" v3="157"/>
				<face v1="157" v2="158" v3="159"/>
				<face v1="158" v2="160" v3="159"/>
				<face v1="159" v2="160" v3="161"/>
				<face v1="160" v2="162" v3="161"/>
				<face v1="161" v2="162" v3="163"/>
				<face v1="162" v2="164" v3="163"/>
				<face v1="162" v2="165" v3="164"/>
				<face v1="164" v2="165" v3="166"/>
				<face v1="166" v2="165" v3="167"/>
				<face v1="167" v2="165" v3="168"/>
				<face v1="165" v2="169" v3="168"/>
			</faces>
			<geometry vertexcount="170">
				<vertexbuffer positions="true" normals="true">
					<vertex>
						<position x="-2308.980469" y="0.000000" z="2811.171631"/>
						<normal x="0.000000" y="1.000000" z="0.000000"/>
					</vertex>
					<vertex>
						<position x="-2310.000000" y="0.000000" z="2811.756348"/>
						<normal x="0.000000" y="1.000000" z="0.000000"/>
					</vertex>
					<vertex>
						<position x="-2310.000000" y="0.000000" z="2820.000000"/>
						<normal x="0.000000" y="1.000000" z="0.000000"/>
					</vertex>
					<vertex>
						<position x="-2294.886719" y="0.000000" z="2803.091309"/>
						<normal x="0.000000" y="1.000000" z="0.000000"/>
					</vertex>
					<vertex>
						<position x="-2280.000000" y="0.000000" z="2820.000000"/>
						<normal x="0.000000" y="1.000000" z="0.000000"/>
					</vertex>
					<vertex>
						<position x="-2285.536133" y="0.000000" z="2798.724365"/>
						<normal x="0.000000" y="1.000000" z="-0.000000"/>
					</vertex>
					<vertex>
						<position x="-2271.204590" y="0.000000" z="2793.434570"/>
						<normal x="-0.000000" y="1.000000" z="0.000000"/>
					</vertex>
					<vertex>
						<position x="-2250.000000" y="0.000000" z="2820.000000"/>
						<normal x="0.000000" y="1.000000" z="-0.000000"/>
					</vertex>
					<vertex>
						<position x="-2263.182861" y="0.000000" z="2791.707764"/>
						<normal x="0.000000" y="1.000000" z="-0.000000"/>
					</vertex>
					<vertex>
						<position x="-2252.278076" y="0.000000" z="2789.796631"/>
						<normal x="0.000000" y="1.000000" z="-0.000000"/>
					</vertex>
					<vertex>
						<position x="-2250.000000" y="0.000000" z="2790.000000"/>
						<normal x="0.000000" y="1.000000" z="-0.000000"/>
					</vertex>
					<vertex>
						<position x="-2220.000000" y="0.000000" z="2820.000000"/>
						<normal x="0.000000" y="1.000000" z="0.000000"/>
					</vertex>
					<vertex>
						<position x="-2202.002930" y="0.000000" z="2783.000000"/>
						<normal x="-0.000000" y="1.000000" z="0.000000"/>
					</vertex>
					<vertex>
						<position x="-2220.000000" y="0.000000" z="2790.000000"/>
						<normal x="0.000000" y="1.000000" z="0.000000"/>
					</vertex>
					<vertex>
						<position x="-2190.000000" y="0.000000" z="2820.000000"/>
						<normal x="0.000000" y="1.000000" z="0.000000"/>
					</vertex>
					<vertex>
						<position x="-2190.000000" y="0.000000" z="2790.000000"/>
						<normal x="0.000000" y="1.000000" z="-0.000000"/>
					</vertex>
					<vertex>
						<position x="-2160.000000" y="0.000000" z="2790.000000"/>
						<normal x="0.000000" y="1.000000" z="0.000000"/>
					</vertex>
					<vertex>
						<position x="-2160.000000" y="0.000000" z="2820.000000"/>
						<normal x="0.000000" y="1.000000" z="0.000000"/>
					</vertex>
					<vertex>
						<position x="-2119.890869" y="0.000000" z="2773.954590"/>
						<normal x="0.000000" y="1.000000" z="0.000000"/>
					</vertex>
					<vertex>
						<position x="-2130.000000" y="0.000000" z="2820.000000"/>
						<normal x="0.000000" y="1.000000" z="0.000000"/>
					</vertex>
					<vertex>
						<position x="-2130.000000" y="0.000000" z="2790.000000"/>
						<normal x="-0.000000" y="1.000000" z="0.000000"/>
					</vertex>
					<vertex>
						<position x="-2100.000000" y="0.000000" z="2790.000000"/>
						<normal x="0.000000" y="1.000000" z="-0.000000"/>
					</vertex>
					<vertex>
						<position x="-2100.000000" y="0.000000" z="2820.000000"/>
						<normal x="0.000000" y="1.000000" z="0.000000"/>
					</vertex>
					<vertex>
						<position x="-2100.000000" y="0.000000" z="2760.000000"/>
						<normal x="-0.000000" y="1.000000" z="0.000000"/>
					</vertex>
					<vertex>
						<position x="-2070.000000" y="0.000000" z="2820.000000"/>
						<normal x="0.000000" y="1.000000" z="0.000000"/>
					</vertex>
					<vertex>
						<position x="-2070.000000" y="0.000000" z="2790.000000"/>
						<normal x="0.000000" y="1.000000" z="0.000000"/>
					</vertex>
					<vertex>
						<position x="-2070.000000" y="0.000000" z="2700.000000"/>
						<normal x="0.000000" y="1.000000" z="0.000000"/>
					</vertex>
					<vertex>
						<position x="-2070.000000" y="0.000000" z="2760.000000"/>
						<normal x="0.000000" y="1.000000" z="0.000000"/>
					</vertex>
					<vertex>
						<position x="-2070.000000" y="0.000000" z="2730.000000"/>
						<normal x="0.000000" y="1.000000" z="0.000000"/>
					</vertex>
					<vertex>
						<position x="-2065.397461" y="0.000000" z="2689.408447"/>
						<normal x="0.000000" y="1.000000" z="0.000000"/>
					</vertex>
					<vertex>
						<position x="-2040.000000" y="0.000000" z="2820.000000"/>
						<normal x="0.000000" y="1.000000" z="0.000000"/>
					</vertex>
					<vertex>
						<position x="-2040.000000" y="0.000000" z="2790.000000"/>
						<normal x="0.000000" y="1.000000" z="0.000000"/>
					</vertex>
					<vertex>
						<position x="-2040.000000" y="0.000000" z="2730.000000"/>
						<normal x="0.000000" y="1.000000" z="0.000000"/>
					</vertex>
					<vertex>
						<position x="-2040.000000" y="0.000000" z="2700.000000"/>
						<normal x="0.000000" y="1.000000" z="-0.000000"/>
					</vertex>
					<vertex>
						<position x="-2040.000000" y="0.000000" z="2760.000000"/>
						<normal x="0.000000" y="1.000000" z="0.000000"/>
					</vertex>
					<vertex>
						<position x="-2040.000000" y="0.000000" z="2670.000000"/>
						<normal x="-0.000000" y="1.000000" z="0.000000"/>
					</vertex>
					<vertex>
						<position x="-2010.000000" y="0.000000" z="2820.000000"/>
						<normal x="0.000000" y="1.000000" z="0.000000"/>
					</vertex>
					<vertex>
						<position x="-2010.000000" y="0.000000" z="2790.000000"/>
						<normal x="0.000000" y="1.000000" z="0.000000"/>
					</vertex>
					<vertex>
						<position x="-2010.000000" y="0.000000" z="2760.000000"/>
						<normal x="0.000000" y="1.000000" z="0.000000"/>
					</vertex>
					<vertex>
						<position x="-2010.000000" y="0.000000" z="2730.000000"/>
						<normal x="0.000000" y="1.000000" z="0.000000"/>
					</vertex>
					<vertex>
						<position x="-2010.000000" y="0.000000" z="2700.000000"/>
						<normal x="0.000000" y="1.000000" z="0.000000"/>
					</vertex>
					<vertex>
						<position x="-2040.000000" y="0.000000" z="2640.000000"/>
						<normal x="0.000000" y="1.000000" z="0.000000"/>
					</vertex>
					<vertex>
						<position x="-2010.000000" y="0.000000" z="2670.000000"/>
						<normal x="0.000000" y="1.000000" z="0.000000"/>
					</vertex>
					<vertex>
						<position x="-2020.497681" y="0.000000" z="2592.062744"/>
						<normal x="0.000000" y="1.000000" z="0.000000"/>
					</vertex>
					<vertex>
						<position x="-2010.000000" y="0.000000" z="2640.000000"/>
						<normal x="0.000000" y="1.000000" z="0.000000"/>
					</vertex>
					<vertex>
						<position x="-2010.000000" y="0.000000" z="2610.000000"/>
						<normal x="0.000000" y="1.000000" z="-0.000000"/>
					</vertex>
					<vertex>
						<position x="-2010.000000" y="0.000000" z="2581.757813"/>
						<normal x="-0.000000" y="1.000000" z="0.000000"/>
					</vertex>
					<vertex>
						<position x="-2310.000000" y="0.000000" z="2520.000000"/>
						<normal x="0.000000" y="1.000000" z="0.000000"/>
					</vertex>
					<vertex>
						<position x="-2280.000000" y="0.000000" z="2550.000000"/>
						<normal x="0.000000" y="1.000000" z="0.000000"/>
					</vertex>
					<vertex>
						<position x="-2280.000000" y="0.000000" z="2520.000000"/>
						<normal x="0.000000" y="1.000000" z="0.000000"/>
					</vertex>
					<vertex>
						<position x="-2250.000000" y="0.000000" z="2550.000000"/>
						<normal x="0.000000" y="1.000000" z="0.000000"/>
					</vertex>
					<vertex>
						<position x="-2310.000000" y="0.000000" z="2550.000000"/>
						<normal x="0.000000" y="1.000000" z="0.000000"/>
					</vertex>
					<vertex>
						<position x="-2250.000000" y="0.000000" z="2580.000000"/>
						<normal x="0.000000" y="1.000000" z="0.000000"/>
					</vertex>
					<vertex>
						<position x="-2250.000000" y="0.000000" z="2520.000000"/>
						<normal x="0.000000" y="1.000000" z="0.000000"/>
					</vertex>
					<vertex>
						<position x="-2280.000000" y="0.000000" z="2580.000000"/>
						<normal x="0.000000" y="1.000000" z="0.000000"/>
					</vertex>
					<vertex>
						<position x="-2220.000000" y="0.000000" z="2580.000000"/>
						<normal x="0.000000" y="1.000000" z="0.000000"/>
					</vertex>
					<vertex>
						<position x="-2220.000000" y="0.000000" z="2550.000000"/>
						<normal x="0.000000" y="1.000000" z="0.000000"/>
					</vertex>
					<vertex>
						<position x="-2310.000000" y="0.000000" z="2580.000000"/>
						<normal x="0.000000" y="1.000000" z="0.000000"/>
					</vertex>
					<vertex>
						<position x="-2220.000000" y="0.000000" z="2610.000000"/>
						<normal x="0.000000" y="1.000000" z="0.000000"/>
					</vertex>
					<vertex>
						<position x="-2250.000000" y="0.000000" z="2610.000000"/>
						<normal x="0.000000" y="1.000000" z="0.000000"/>
					</vertex>
					<vertex>
						<position x="-2220.000000" y="0.000000" z="2520.000000"/>
						<normal x="0.000000" y="1.000000" z="0.000000"/>
					</vertex>
					<vertex>
						<position x="-2280.000000" y="0.000000" z="2610.000000"/>
						<normal x="0.000000" y="1.000000" z="0.000000"/>
					</vertex>
					<vertex>
						<position x="-2190.000000" y="0.000000" z="2610.000000"/>
						<normal x="0.000000" y="1.000000" z="0.000000"/>
					</vertex>
					<vertex>
						<position x="-2190.000000" y="0.000000" z="2580.000000"/>
						<normal x="0.000000" y="1.000000" z="0.000000"/>
					</vertex>
					<vertex>
						<position x="-2190.000000" y="0.000000" z="2550.000000"/>
						<normal x="0.000000" y="1.000000" z="0.000000"/>
					</vertex>
					<vertex>
						<position x="-2310.000000" y="0.000000" z="2610.000000"/>
						<normal x="0.000000" y="1.000000" z="0.000000"/>
					</vertex>
					<vertex>
						<position x="-2190.000000" y="0.000000" z="2640.000000"/>
						<normal x="0.000000" y="1.000000" z="0.000000"/>
					</vertex>
					<vertex>
						<position x="-2220.000000" y="0.000000" z="2640.000000"/>
						<normal x="0.000000" y="1.000000" z="0.000000"/>
					</vertex>
					<vertex>
						<position x="-2250.000000" y="0.000000" z="2640.000000"/>
						<normal x="0.000000" y="1.000000" z="0.000000"/>
					</vertex>
					<vertex>
						<position x="-2190.000000" y="0.000000" z="2520.000000"/>
						<normal x="0.000000" y="1.000000" z="0.000000"/>
					</vertex>
					<vertex>
						<position x="-2280.000000" y="0.000000" z="2640.000000"/>
						<normal x="0.000000" y="1.000000" z="0.000000"/>
					</vertex>
					<vertex>
						<position x="-2160.000000" y="0.000000" z="2640.000000"/>
						<normal x="0.000000" y="1.000000" z="0.000000"/>
					</vertex>
					<vertex>
						<position x="-2160.000000" y="0.000000" z="2610.000000"/>
						<normal x="0.000000" y="1.000000" z="0.000000"/>
					</vertex>
					<vertex>
						<position x="-2160.000000" y="0.000000" z="2580.000000"/>
						<normal x="0.000000" y="1.000000" z="0.000000"/>
					</vertex>
					<vertex>
						<position x="-2160.000000" y="0.000000" z="2550.000000"/>
						<normal x="0.000000" y="1.000000" z="0.000000"/>
					</vertex>
					<vertex>
						<position x="-2310.000000" y="0.000000" z="2640.000000"/>
						<normal x="0.000000" y="1.000000" z="0.000000"/>
					</vertex>
					<vertex>
						<position x="-2160.000000" y="0.000000" z="2670.000000"/>
						<normal x="0.000000" y="1.000000" z="0.000000"/>
					</vertex>
					<vertex>
						<position x="-2190.000000" y="0.000000" z="2670.000000"/>
						<normal x="0.000000" y="1.000000" z="0.000000"/>
					</vertex>
					<vertex>
						<position x="-2220.000000" y="0.000000" z="2670.000000"/>
						<normal x="0.000000" y="1.000000" z="0.000000"/>
					</vertex>
					<vertex>
						<position x="-2250.000000" y="0.000000" z="2670.000000"/>
						<normal x="0.000000" y="1.000000" z="0.000000"/>
					</vertex>
					<vertex>
						<position x="-2160.000000" y="0.000000" z="2520.000000"/>
						<normal x="0.000000" y="1.000000" z="0.000000"/>
					</vertex>
					<vertex>
						<position x="-2310.000000" y="0.000000" z="2654.442383"/>
						<normal x="0.000000" y="1.000000" z="0.000000"/>
					</vertex>
					<vertex>
						<position x="-2130.000000" y="0.000000" z="2670.000000"/>
						<normal x="0.000000" y="1.000000" z="0.000000"/>
					</vertex>
					<vertex>
						<position x="-2130.000000" y="0.000000" z="2640.000000"/>
						<normal x="0.000000" y="1.000000" z="0.000000"/>
					</vertex>
					<vertex>
						<position x="-2130.000000" y="0.000000" z="2610.000000"/>
						<normal x="0.000000" y="1.000000" z="0.000000"/>
					</vertex>
					<vertex>
						<position x="-2130.000000" y="0.000000" z="2580.000000"/>
						<normal x="0.000000" y="1.000000" z="0.000000"/>
					</vertex>
					<vertex>
						<position x="-2280.000000" y="0.000000" z="2670.000000"/>
						<normal x="0.000000" y="1.000000" z="0.000000"/>
					</vertex>
					<vertex>
						<position x="-2130.000000" y="0.000000" z="2550.000000"/>
						<normal x="0.000000" y="1.000000" z="0.000000"/>
					</vertex>
					<vertex>
						<position x="-2308.053467" y="0.000000" z="2660.326660"/>
						<normal x="0.000000" y="1.000000" z="0.000000"/>
					</vertex>
					<vertex>
						<position x="-2130.000000" y="0.000000" z="2700.000000"/>
						<normal x="0.000000" y="1.000000" z="0.000000"/>
					</vertex>
					<vertex>
						<position x="-2160.000000" y="0.000000" z="2700.000000"/>
						<normal x="0.000000" y="1.000000" z="0.000000"/>
					</vertex>
					<vertex>
						<position x="-2190.000000" y="0.000000" z="2700.000000"/>
						<normal x="0.000000" y="1.000000" z="0.000000"/>
					</vertex>
					<vertex>
						<position x="-2220.000000" y="0.000000" z="2700.000000"/>
						<normal x="0.000000" y="1.000000" z="0.000000"/>
					</vertex>
					<vertex>
						<position x="-2250.000000" y="0.000000" z="2700.000000"/>
						<normal x="0.000000" y="1.000000" z="0.000000"/>
					</vertex>
					<vertex>
						<position x="-2130.000000" y="0.000000" z="2520.000000"/>
						<normal x="0.000000" y="1.000000" z="0.000000"/>
					</vertex>
					<vertex>
						<position x="-2100.000000" y="0.000000" z="2700.000000"/>
						<normal x="0.000000" y="1.000000" z="0.000000"/>
					</vertex>
					<vertex>
						<position x="-2100.000000" y="0.000000" z="2670.000000"/>
						<normal x="0.000000" y="1.000000" z="0.000000"/>
					</vertex>
					<vertex>
						<position x="-2100.000000" y="0.000000" z="2640.000000"/>
						<normal x="0.000000" y="1.000000" z="0.000000"/>
					</vertex>
					<vertex>
						<position x="-2100.000000" y="0.000000" z="2610.000000"/>
						<normal x="0.000000" y="1.000000" z="0.000000"/>
					</vertex>
					<vertex>
						<position x="-2100.000000" y="0.000000" z="2580.000000"/>
						<normal x="0.000000" y="1.000000" z="0.000000"/>
					</vertex>
					<vertex>
						<position x="-2280.000000" y="0.000000" z="2700.000000"/>
						<normal x="0.000000" y="1.000000" z="0.000000"/>
					</vertex>
					<vertex>
						<position x="-2303.994873" y="0.000000" z="2672.611572"/>
						<normal x="0.000000" y="1.000000" z="0.000000"/>
					</vertex>
					<vertex>
						<position x="-2100.000000" y="0.000000" z="2550.000000"/>
						<normal x="0.000000" y="1.000000" z="0.000000"/>
					</vertex>
					<vertex>
						<position x="-2100.000000" y="0.000000" z="2730.000000"/>
						<normal x="0.000000" y="1.000000" z="0.000000"/>
					</vertex>
					<vertex>
						<position x="-2130.000000" y="0.000000" z="2730.000000"/>
						<normal x="0.000000" y="1.000000" z="0.000000"/>
					</vertex>
					<vertex>
						<position x="-2160.000000" y="0.000000" z="2730.000000"/>
						<normal x="0.000000" y="1.000000" z="0.000000"/>
					</vertex>
					<vertex>
						<position x="-2190.000000" y="0.000000" z="2730.000000"/>
						<normal x="0.000000" y="1.000000" z="0.000000"/>
					</vertex>
					<vertex>
						<position x="-2220.000000" y="0.000000" z="2730.000000"/>
						<normal x="0.000000" y="1.000000" z="0.000000"/>
					</vertex>
					<vertex>
						<position x="-2250.000000" y="0.000000" z="2730.000000"/>
						<normal x="0.000000" y="1.000000" z="0.000000"/>
					</vertex>
					<vertex>
						<position x="-2100.000000" y="0.000000" z="2520.000000"/>
						<normal x="0.000000" y="1.000000" z="0.000000"/>
					</vertex>
					<vertex>
						<position x="-2068.992676" y="0.000000" z="2687.437500"/>
						<normal x="0.000000" y="1.000000" z="0.000000"/>
					</vertex>
					<vertex>
						<position x="-2070.000000" y="0.000000" z="2670.000000"/>
						<normal x="0.000000" y="1.000000" z="0.000000"/>
					</vertex>
					<vertex>
						<position x="-2070.000000" y="0.000000" z="2640.000000"/>
						<normal x="0.000000" y="1.000000" z="0.000000"/>
					</vertex>
					<vertex>
						<position x="-2070.000000" y="0.000000" z="2610.000000"/>
						<normal x="0.000000" y="1.000000" z="0.000000"/>
					</vertex>
					<vertex>
						<position x="-2070.000000" y="0.000000" z="2580.000000"/>
						<normal x="0.000000" y="1.000000" z="0.000000"/>
					</vertex>
					<vertex>
						<position x="-2280.000000" y="0.000000" z="2730.000000"/>
						<normal x="0.000000" y="1.000000" z="0.000000"/>
					</vertex>
					<vertex>
						<position x="-2293.266602" y="0.000000" z="2711.629639"/>
						<normal x="0.000000" y="1.000000" z="0.000000"/>
					</vertex>
					<vertex>
						<position x="-2070.000000" y="0.000000" z="2550.000000"/>
						<normal x="0.000000" y="1.000000" z="0.000000"/>
					</vertex>
					<vertex>
						<position x="-2122.047119" y="0.000000" z="2770.467285"/>
						<normal x="0.000000" y="1.000000" z="0.000000"/>
					</vertex>
					<vertex>
						<position x="-2130.000000" y="0.000000" z="2760.000000"/>
						<normal x="0.000000" y="1.000000" z="0.000000"/>
					</vertex>
					<vertex>
						<position x="-2160.000000" y="0.000000" z="2760.000000"/>
						<normal x="0.000000" y="1.000000" z="0.000000"/>
					</vertex>
					<vertex>
						<position x="-2190.000000" y="0.000000" z="2760.000000"/>
						<normal x="0.000000" y="1.000000" z="0.000000"/>
					</vertex>
					<vertex>
						<position x="-2220.000000" y="0.000000" z="2760.000000"/>
						<normal x="0.000000" y="1.000000" z="0.000000"/>
					</vertex>
					<vertex>
						<position x="-2282.107910" y="0.000000" z="2750.365234"/>
						<normal x="0.000000" y="1.000000" z="0.000000"/>
					</vertex>
					<vertex>
						<position x="-2070.000000" y="0.000000" z="2520.000000"/>
						<normal x="0.000000" y="1.000000" z="0.000000"/>
					</vertex>
					<vertex>
						<position x="-2040.000000" y="0.000000" z="2610.000000"/>
						<normal x="0.000000" y="1.000000" z="0.000000"/>
					</vertex>
					<vertex>
						<position x="-2250.000000" y="0.000000" z="2760.000000"/>
						<normal x="0.000000" y="1.000000" z="0.000000"/>
					</vertex>
					<vertex>
						<position x="-2040.000000" y="0.000000" z="2580.000000"/>
						<normal x="0.000000" y="1.000000" z="0.000000"/>
					</vertex>
					<vertex>
						<position x="-2040.000000" y="0.000000" z="2550.000000"/>
						<normal x="0.000000" y="1.000000" z="0.000000"/>
					</vertex>
					<vertex>
						<position x="-2023.852295" y="0.000000" z="2589.705322"/>
						<normal x="0.000000" y="1.000000" z="0.000000"/>
					</vertex>
					<vertex>
						<position x="-2202.497070" y="0.000000" z="2778.929932"/>
						<normal x="0.000000" y="1.000000" z="0.000000"/>
					</vertex>
					<vertex>
						<position x="-2252.827393" y="0.000000" z="2785.733643"/>
						<normal x="0.000000" y="1.000000" z="0.000000"/>
					</vertex>
					<vertex>
						<position x="-2276.291992" y="0.000000" z="2766.907227"/>
						<normal x="0.000000" y="1.000000" z="0.000000"/>
					</vertex>
					<vertex>
						<position x="-2040.000000" y="0.000000" z="2520.000000"/>
						<normal x="0.000000" y="1.000000" z="0.000000"/>
					</vertex>
					<vertex>
						<position x="-2261.910889" y="0.000000" z="2783.888672"/>
						<normal x="-0.000000" y="1.000000" z="0.000000"/>
					</vertex>
					<vertex>
						<position x="-2011.438965" y="0.000000" z="2577.425049"/>
						<normal x="0.000000" y="1.000000" z="0.000000"/>
					</vertex>
					<vertex>
						<position x="-2274.510254" y="0.000000" z="2771.197266"/>
						<normal x="-0.000000" y="1.000000" z="0.000000"/>
					</vertex>
					<vertex>
						<position x="-2010.000000" y="0.000000" z="2550.000000"/>
						<normal x="0.000000" y="1.000000" z="0.000000"/>
					</vertex>
					<vertex>
						<position x="-2264.686523" y="0.000000" z="2782.255615"/>
						<normal x="-0.000000" y="1.000000" z="0.000000"/>
					</vertex>
					<vertex>
						<position x="-2270.973145" y="0.000000" z="2776.504150"/>
						<normal x="-0.000000" y="1.000000" z="0.000000"/>
					</vertex>
					<vertex>
						<position x="-2010.000000" y="0.000000" z="2520.000000"/>
						<normal x="0.000000" y="1.000000" z="0.000000"/>
					</vertex>
					<vertex>
						<position x="-2010.000000" y="0.000000" z="2576.007080"/>
						<normal x="0.000000" y="1.000000" z="0.000000"/>
					</vertex>
					<vertex>
						<position x="-2282.880371" y="0.000000" z="2785.288574"/>
						<normal x="0.000000" y="1.000000" z="-0.000000"/>
					</vertex>
					<vertex>
						<position x="-2287.167480" y="0.000000" z="2794.647461"/>
						<normal x="0.000000" y="1.000000" z="-0.000000"/>
					</vertex>
					<vertex>
						<position x="-2280.000000" y="0.000000" z="2790.000000"/>
						<normal x="0.000000" y="1.000000" z="-0.000000"/>
					</vertex>
					<vertex>
						<position x="-2286.954590" y="0.000000" z="2794.877686"/>
						<normal x="0.000000" y="1.000000" z="0.000000"/>
					</vertex>
					<vertex>
						<position x="-2274.084961" y="0.000000" z="2779.173828"/>
						<normal x="-0.000000" y="1.000000" z="0.000000"/>
					</vertex>
					<vertex>
						<position x="-2272.349365" y="0.000000" z="2789.497559"/>
						<normal x="0.000000" y="1.000000" z="0.000000"/>
					</vertex>
					<vertex>
						<position x="-2280.526855" y="0.000000" z="2773.381348"/>
						<normal x="0.000000" y="1.000000" z="-0.000000"/>
					</vertex>
					<vertex>
						<position x="-2267.129395" y="0.000000" z="2785.548340"/>
						<normal x="0.000000" y="1.000000" z="0.000000"/>
					</vertex>
					<vertex>
						<position x="-2278.123535" y="0.000000" z="2773.134766"/>
						<normal x="0.000000" y="1.000000" z="-0.000000"/>
					</vertex>
					<vertex>
						<position x="-2264.048096" y="0.000000" z="2787.700195"/>
						<normal x="0.000000" y="1.000000" z="-0.000000"/>
					</vertex>
					<vertex>
						<position x="-2280.075195" y="0.000000" z="2768.487549"/>
						<normal x="0.000000" y="1.000000" z="0.000000"/>
					</vertex>
					<vertex>
						<position x="-2264.001709" y="0.000000" z="2787.415283"/>
						<normal x="0.000000" y="1.000000" z="0.000000"/>
					</vertex>
					<vertex>
						<position x="-2280.184570" y="0.000000" z="2768.505615"/>
						<normal x="0.000000" y="1.000000" z="0.000000"/>
					</vertex>
					<vertex>
						<position x="-2310.000000" y="0.000000" z="2667.502441"/>
						<normal x="0.000000" y="1.000000" z="0.000000"/>
					</vertex>
					<vertex>
						<position x="-2310.000000" y="0.000000" z="2670.000000"/>
						<normal x="0.000000" y="1.000000" z="0.000000"/>
					</vertex>
					<vertex>
						<position x="-2307.919189" y="0.000000" z="2673.798584"/>
						<normal x="0.000000" y="1.000000" z="0.000000"/>
					</vertex>
					<vertex>
						<position x="-2310.000000" y="0.000000" z="2700.000000"/>
						<normal x="0.000000" y="1.000000" z="0.000000"/>
					</vertex>
					<vertex>
						<position x="-2297.213379" y="0.000000" z="2712.740479"/>
						<normal x="0.000000" y="1.000000" z="-0.000000"/>
					</vertex>
					<vertex>
						<position x="-2310.000000" y="0.000000" z="2730.000000"/>
						<normal x="0.000000" y="1.000000" z="0.000000"/>
					</vertex>
					<vertex>
						<position x="-2286.047607" y="0.000000" z="2751.500244"/>
						<normal x="0.000000" y="1.000000" z="-0.000000"/>
					</vertex>
					<vertex>
						<position x="-2310.000000" y="0.000000" z="2760.000000"/>
						<normal x="0.000000" y="1.000000" z="0.000000"/>
					</vertex>
					<vertex>
						<position x="-2284.274902" y="0.000000" z="2768.221924"/>
						<normal x="0.000000" y="1.000000" z="-0.000000"/>
					</vertex>
					<vertex>
						<position x="-2284.591309" y="0.000000" z="2772.842773"/>
						<normal x="0.000000" y="1.000000" z="0.000000"/>
					</vertex>
					<vertex>
						<position x="-2310.000000" y="0.000000" z="2790.000000"/>
						<normal x="0.000000" y="1.000000" z="0.000000"/>
					</vertex>
					<vertex>
						<position x="-2286.781738" y="0.000000" z="2784.027588"/>
						<normal x="0.000000" y="1.000000" z="0.000000"/>
					</vertex>
					<vertex>
						<position x="-2290.892822" y="0.000000" z="2792.934814"/>
						<normal x="0.000000" y="1.000000" z="0.000000"/>
					</vertex>
					<vertex>
						<position x="-2296.926025" y="0.000000" z="2799.534424"/>
						<normal x="0.000000" y="1.000000" z="0.000000"/>
					</vertex>
					<vertex>
						<position x="-2310.000000" y="0.000000" z="2807.030273"/>
						<normal x="0.000000" y="1.000000" z="0.000000"/>
					</vertex>
				</vertexbuffer>
			</geometry>
		</submesh>
	</submeshes>
</mesh>
