<mesh>
	<submeshes>
		<submesh material="ASPHALT_0.001" usesharedvertices="false">
			<faces count="4">
				<face v1="0" v2="1" v3="2"/>
				<face v1="1" v2="3" v3="2"/>
				<face v1="4" v2="5" v3="6"/>
				<face v1="5" v2="7" v3="6"/>
			</faces>
			<geometry vertexcount="8">
				<vertexbuffer positions="true" normals="true">
					<vertex>
						<position x="-55.056526" y="0.000000" z="411.982422"/>
						<normal x="0.000000" y="1.000000" z="0.000000"/>
					</vertex>
					<vertex>
						<position x="-57.051136" y="0.000000" z="411.835663"/>
						<normal x="0.000000" y="1.000000" z="0.000000"/>
					</vertex>
					<vertex>
						<position x="-56.340698" y="0.000000" z="450.483124"/>
						<normal x="0.000000" y="1.000000" z="0.000000"/>
					</vertex>
					<vertex>
						<position x="-58.338066" y="0.000000" z="450.380554"/>
						<normal x="0.000000" y="1.000000" z="-0.000000"/>
					</vertex>
					<vertex>
						<position x="-57.150864" y="0.000000" z="411.828339"/>
						<normal x="0.000000" y="1.000000" z="0.000000"/>
					</vertex>
					<vertex>
						<position x="-59.145473" y="0.000000" z="411.681580"/>
						<normal x="0.000000" y="1.000000" z="0.000000"/>
					</vertex>
					<vertex>
						<position x="-58.437935" y="0.000000" z="450.375427"/>
						<normal x="0.000000" y="1.000000" z="0.000000"/>
					</vertex>
					<vertex>
						<position x="-60.435303" y="0.000000" z="450.272858"/>
						<normal x="0.000000" y="1.000000" z="-0.000000"/>
					</vertex>
				</vertexbuffer>
			</geometry>
		</submesh>
	</submeshes>
</mesh>
