<mesh>
	<submeshes>
		<submesh material="ASPHALT_0.001" usesharedvertices="false">
			<faces count="4">
				<face v1="0" v2="1" v3="2"/>
				<face v1="1" v2="3" v3="2"/>
				<face v1="2" v2="3" v3="4"/>
				<face v1="3" v2="5" v3="4"/>
			</faces>
			<geometry vertexcount="6">
				<vertexbuffer positions="true" normals="true">
					<vertex>
						<position x="-90.970772" y="0.000000" z="-487.278351"/>
						<normal x="-0.000000" y="1.000000" z="0.000000"/>
					</vertex>
					<vertex>
						<position x="-90.151230" y="0.000000" z="-483.875641"/>
						<normal x="-0.000000" y="1.000000" z="0.000000"/>
					</vertex>
					<vertex>
						<position x="-90.587883" y="0.000000" z="-487.425385"/>
						<normal x="-0.000000" y="1.000000" z="0.000000"/>
					</vertex>
					<vertex>
						<position x="-89.412117" y="0.000000" z="-484.128784"/>
						<normal x="0.000000" y="1.000000" z="0.000000"/>
					</vertex>
					<vertex>
						<position x="-87.583145" y="0.000000" z="-488.489166"/>
						<normal x="-0.000000" y="1.000000" z="0.000000"/>
					</vertex>
					<vertex>
						<position x="-86.108856" y="0.000000" z="-485.314819"/>
						<normal x="0.000000" y="1.000000" z="0.000000"/>
					</vertex>
				</vertexbuffer>
			</geometry>
		</submesh>
	</submeshes>
</mesh>
